README.rst
setup.py
sudoku/__init__.py
sudoku/cli.py
sudoku/exceptions.py
sudoku/serialization.py
sudoku/solver.py
sudoku_cli.egg-info/PKG-INFO
sudoku_cli.egg-info/SOURCES.txt
sudoku_cli.egg-info/dependency_links.txt
sudoku_cli.egg-info/entry_points.txt
sudoku_cli.egg-info/requires.txt
sudoku_cli.egg-info/top_level.txt