Metadata-Version: 1.0
Name: sudoku-cli
Version: 0.6
Summary: A CLI tool for solving sudoku puzzles.
Home-page: https://github.com/lukegrecki/sudoku-cli
Author: Luke Grecki
Author-email: lukegrecki@gmail.com
License: UNKNOWN
Keywords: sudoku
Platform: UNKNOWN
